prompt_defender_llm_defences/__init__.py
prompt_defender_llm_defences/keep/__init__.py
prompt_defender_llm_defences/keep/keep_langchain.py
prompt_defender_llm_defences/tests/__init__.py
prompt_defender_llm_defences/tests/config.py
prompt_defender_llm_defences/tests/test_llm_based_prehand.py
prompt_defender_llm_defences/tests/test_paraphrasing_defence.py
prompt_defender_llm_defences/tests/test_proactive_defence.py
prompt_defender_llm_defences/wall/__init__.py
prompt_defender_llm_defences/wall/llm_prehand_defence.py
prompt_defender_llm_defences/wall/paraphrasing_defence.py
prompt_defender_llm_defences/wall/proactive_defence.py
prompt_defender_llm_defences-0.1.26.dist-info/METADATA
prompt_defender_llm_defences-0.1.26.dist-info/WHEEL
prompt_defender_llm_defences-0.1.26.dist-info/RECORD
